opxrd/__init__.py
opxrd/database/__init__.py
opxrd/database/database.py
opxrd/submission_helper/app.py
opxrd/submission_helper/configs/__init__.py
opxrd/submission_helper/configs/conf.py
opxrd/submission_helper/elements/__init__.py
opxrd/submission_helper/elements/loadable_element.py
opxrd/submission_helper/elements/node_element.py
opxrd/submission_helper/elements/node_widget.py
opxrd/submission_helper/elements/types.py
opxrd/submission_helper/filesystem/__init__.py
opxrd/submission_helper/filesystem/fsnode.py
opxrd/submission_helper/filesystem/lib.py
opxrd/submission_helper/filesystem/out_files.py
opxrd/submission_helper/layouts/__init__.py
opxrd/submission_helper/layouts/dialogue.py
opxrd/submission_helper/layouts/finish.py
opxrd/submission_helper/layouts/selection.py
opxrd/submission_helper/resources/__init__.py
opxrd/submission_helper/resources/resource_manager.py
opxrd/submission_helper/run/dev_run.py
opxrd/submission_helper/run/prod_run.py
opxrd-0.1.0.dist-info/METADATA
opxrd-0.1.0.dist-info/WHEEL
opxrd-0.1.0.dist-info/top_level.txt
opxrd-0.1.0.dist-info/RECORD
